django_dowser/__init__.py
django_dowser/reftree.py
django_dowser/urls.py
django_dowser/views.py
django_dowser/templates/django_dowser/base.html
django_dowser/templates/django_dowser/graphs.html
django_dowser/templates/django_dowser/main.css
django_dowser/templates/django_dowser/trace.html
django_dowser/templates/django_dowser/tree.html
django_dowser-0.1.8.dist-info/LICENSE
django_dowser-0.1.8.dist-info/METADATA
django_dowser-0.1.8.dist-info/WHEEL
django_dowser-0.1.8.dist-info/top_level.txt
django_dowser-0.1.8.dist-info/RECORD
