Metadata-Version: 2.1
Name: django-dowser
Version: 0.1.8
Summary: Django fork of amazing memory leaks tracking application for python wsgi - the Dowser
Home-page: http://github.com/munhitsu/django-dowser
Author: Mateusz Lapsa-Malawski
Author-email: m@cr3.io
License: UNKNOWN
Keywords: django,dowser,debug,memory leak
Platform: UNKNOWN
Classifier: Programming Language :: Python
Classifier: Programming Language :: Python :: 2.7
Classifier: Programming Language :: Python :: 3
Classifier: Programming Language :: Python :: 3.7
Classifier: Intended Audience :: Developers
Classifier: Operating System :: OS Independent
Classifier: Topic :: Software Development :: Debuggers
Classifier: License :: OSI Approved :: MIT License
